{
  "main": {
    "id": "3b2b32a6324ebbe2",
    "type": "split",
    "children": [
      {
        "id": "e0e55eeed9cedb2c",
        "type": "tabs",
        "children": [
          {
            "id": "e1153766a1e2e991",
            "type": "leaf",
            "state": {
              "type": "split-diff-view",
              "state": {
                "aFile": "Resumos/EP/02_Estatistica_Descritiva.md",
                "bFile": "Resumos/EP/02_Estatistica_Descritiva.md",
                "aRef": ""
              },
              "icon": "diff",
              "title": "Diff: 02_Estatistica_Descritiva"
            }
          }
        ]
      }
    ],
    "direction": "vertical"
  },
  "left": {
    "id": "ca2f74ade9cd548e",
    "type": "split",
    "children": [
      {
        "id": "f6b46665476a960f",
        "type": "tabs",
        "children": [
          {
            "id": "d7dd2bd579630368",
            "type": "leaf",
            "state": {
              "type": "file-explorer",
              "state": {
                "sortOrder": "alphabetical",
                "autoReveal": false
              },
              "icon": "lucide-folder-closed",
              "title": "Explorador de arquivos"
            }
          },
          {
            "id": "7886ab30dcb307e1",
            "type": "leaf",
            "state": {
              "type": "search",
              "state": {
                "query": "",
                "matchingCase": false,
                "explainSearch": false,
                "collapseAll": false,
                "extraContext": false,
                "sortOrder": "alphabetical"
              },
              "icon": "lucide-search",
              "title": "Procurar"
            }
          },
          {
            "id": "f107faf65d5e56e6",
            "type": "leaf",
            "state": {
              "type": "bookmarks",
              "state": {},
              "icon": "lucide-bookmark",
              "title": "Marcadores"
            }
          }
        ]
      }
    ],
    "direction": "horizontal",
    "width": 241.5
  },
  "right": {
    "id": "c8659ee5e109d427",
    "type": "split",
    "children": [
      {
        "id": "f525f8662a5db1bb",
        "type": "tabs",
        "children": [
          {
            "id": "4df298676d3dd915",
            "type": "leaf",
            "state": {
              "type": "outline",
              "state": {
                "followCursor": false,
                "showSearch": false,
                "searchQuery": ""
              },
              "icon": "lucide-list",
              "title": "Sumário"
            }
          },
          {
            "id": "d5a731bd8c6b5141",
            "type": "leaf",
            "state": {
              "type": "calendar",
              "state": {},
              "icon": "calendar-with-checkmark",
              "title": "Calendar"
            }
          },
          {
            "id": "c50a4587ba2a66a5",
            "type": "leaf",
            "state": {
              "type": "git-view",
              "state": {},
              "icon": "git-pull-request",
              "title": "Source Control"
            }
          }
        ],
        "currentTab": 2
      }
    ],
    "direction": "horizontal",
    "width": 252.5
  },
  "left-ribbon": {
    "hiddenItems": {
      "switcher:Abrir a troca rápida": false,
      "graph:Abrir visualização em gráfico": false,
      "canvas:Criar novo canvas": false,
      "daily-notes:Abrir a nota de hoje": false,
      "templates:Inserir modelo": false,
      "command-palette:Abrir paleta de comandos": false,
      "obsidian-git:Open Git source control": false
    }
  },
  "active": "e1153766a1e2e991",
  "lastOpenFiles": [
    "EP/02_Estatistica_Descritiva.md",
    "Pasted image 20250403203201.png",
    "EP/00_Sumario_EP.md",
    "EP/images/exemplo_boxplot.png",
    "EP/images/exemplo_diagrama_de_ramos_e_folhas.png",
    "EP/images/exemplo_diagrama_de_pontos.png",
    "EP/images/representacao_quartis.png",
    "EP/01_Introdução.md",
    "AEDs_III/01_Arvore_B_B+.md",
    "AEDs_III/00_Sumario_AED3.md",
    "AC_I/00_Sumario_AC1.md",
    "TESTE.md",
    "EP/images/ex_grafico_de_barras.png",
    "EP/images",
    "EP",
    "Nova pasta",
    "AC_I/01_Sistemas_de_Numeracao.md",
    "LP/00_Sumario_LP.md",
    "ES1/01_Diagrama_e_Modularizacao.md",
    "ES1/00_Sumario_ES1.md",
    "IA/01_Introducao_a_Aprendizagem_de_Maquina.md",
    "IA/Images/Machine_Learning_Algorithms_Map.png",
    "IA/02_Arvore_de_Decisao.md",
    "IA/03_Pre_Processamento_de_Dados.md",
    "IA/00_Sumario_IA.md",
    "IA/04_Naive_Bayes.md",
    "LP/04_Sistemas_de_Tipos.md",
    "LP/03_Sequenciadores.md",
    "LP/02_Abstracao_e_Encapsulamento.md",
    "LP/01_Linguagens_de_Programacao.md",
    "AC_I/04_Maquinas_de_Estados.md",
    "AC_I/03_Circuitos_Logicos.md",
    "AC_I/02_Algebra_de_Boole.md",
    "AC_I/images/half_adder.png",
    "Resumos/AC_I/images/full_adder.png.md",
    "Resumos/AC_I/images",
    "Resumos/AC_I",
    "Resumos",
    "ACs/Resumos/Algebra_de_Boole.md",
    "ACs/Resumos",
    "ACs",
    "LP",
    "ES1/Diagrama_e_Modularizacao.txt",
    "AC_I/images/mealy_moore.png",
    "AC_I/images/seq_1101.png",
    "Sem título.canvas"
  ]
}